
[{
    "name": "Refrain",
    "artist": "Anan Ryoko",
    "url": "https://cdn.jsdelivr.net/gh/Zhujie-ww/zhujie-ww.github.io/medias/music/music01.mp3",
    "cover": "https://cdn.jsdelivr.net/gh/Zhujie-ww/zhujie-ww.github.io/medias/music/music01.png"
}, {
    "name": "DJ OKAWARI",
    "artist": "Luv Letter",
    "url": "https://cdn.jsdelivr.net/gh/Zhujie-ww/zhujie-ww.github.io/medias/music/music02.mp3",
    "cover": "https://cdn.jsdelivr.net/gh/Zhujie-ww/zhujie-ww.github.io/medias/music/music03.png"
}, {
    "name": "Foxtail-Grass Studio",
    "artist": "歳月-雲流れ",
    "url": "https://cdn.jsdelivr.net/gh/Zhujie-ww/zhujie-ww.github.io/medias/music/music03.mp3",
    "cover": "https://cdn.jsdelivr.net/gh/Zhujie-ww/zhujie-ww.github.io/medias/music/music02.png"
}]